aicoevolution_sdk.py
aicoevolution-0.0.5.dist-info/METADATA
aicoevolution-0.0.5.dist-info/WHEEL
aicoevolution-0.0.5.dist-info/top_level.txt
aicoevolution-0.0.5.dist-info/RECORD
