Metadata-Version: 2.4
Name: aicoevolution
Version: 0.0.5
Summary: AICoevolution SDK - Semantic Telemetry and Transformation Detection for Human-AI Conversations
Author-email: AICoevolution <contact@aicoevolution.com>
License-Expression: MIT
Project-URL: Homepage, https://aicoevolution.com
Project-URL: Documentation, https://docs.aicoevolution.com
Keywords: ai,telemetry,semantic,conversation,alignment,sdk
Classifier: Development Status :: 3 - Alpha
Classifier: Intended Audience :: Developers
Classifier: Programming Language :: Python :: 3
Classifier: Programming Language :: Python :: 3.8
Classifier: Programming Language :: Python :: 3.9
Classifier: Programming Language :: Python :: 3.10
Classifier: Programming Language :: Python :: 3.11
Classifier: Topic :: Scientific/Engineering :: Artificial Intelligence
Classifier: Topic :: Software Development :: Libraries :: Python Modules
Requires-Python: >=3.8
Requires-Dist: requests>=2.28.0
